ajax_feedback/__init__.py
ajax_feedback/conf.py
ajax_feedback/forms.py
ajax_feedback/send_email.py
ajax_feedback/urls.py
ajax_feedback/views.py
ajax_feedback/locale/ru/LC_MESSAGES/django.mo
ajax_feedback/locale/ru/LC_MESSAGES/django.po
ajax_feedback/static/ajax_feedback/js/jquery.ajax_feedback.js
ajax_feedback/static/ajax_feedback/js/jquery.ajax_feedback.min.js
ajax_feedback/templates/ajax_feedback/contact_form.html
ajax_feedback/templates/ajax_feedback/message.html
ajax_feedback/templates/ajax_feedback/subject.txt
ajax_feedback/templatetags/__init__.py
ajax_feedback/templatetags/ajax_feedback.py
django_ajaxfeedback-0.3.3.dist-info/DESCRIPTION.rst
django_ajaxfeedback-0.3.3.dist-info/METADATA
django_ajaxfeedback-0.3.3.dist-info/RECORD
django_ajaxfeedback-0.3.3.dist-info/WHEEL
django_ajaxfeedback-0.3.3.dist-info/metadata.json
django_ajaxfeedback-0.3.3.dist-info/top_level.txt
