Metadata-Version: 2.0
Name: django-ajaxfeedback
Version: 0.3.3
Summary: Django easy ajax feedback form.
Home-page: https://github.com/evstropov/django-ajax-feedback
Author: Evstropov Nikita
Author-email: evstropov.n@gmail.com
License: UNKNOWN
Platform: UNKNOWN
Classifier: Environment :: Web Environment
Classifier: Intended Audience :: Developers
Classifier: License :: OSI Approved :: Apache Software License
Classifier: Operating System :: OS Independent
Classifier: Programming Language :: Python :: 2.7
Classifier: Framework :: Django
